<?xml version="1.0"?>
<opencv_storage>
<stage4>
  <maxWeakCount>7</maxWeakCount>
  <stageThreshold>-1.1040562391281128e+00</stageThreshold>
  <weakClassifiers>
    <_>
      <internalNodes>
        0 -1 150377 -4.3844796717166901e-02</internalNodes>
      <leafValues>
        8.7306064367294312e-01 -4.7947326302528381e-01</leafValues></_>
    <_>
      <internalNodes>
        0 -1 63370 8.6216079071164131e-03</internalNodes>
      <leafValues>
        -8.8074100017547607e-01 4.5677742362022400e-01</leafValues></_>
    <_>
      <internalNodes>
        0 -1 2105 3.4660792350769043e-01</internalNodes>
      <leafValues>
        -9.2500704526901245e-01 3.4582710266113281e-01</leafValues></_>
    <_>
      <internalNodes>
        0 -1 54625 1.6776474658399820e-03</internalNodes>
      <leafValues>
        3.3784043788909912e-01 -9.5260739326477051e-01</leafValues></_>
    <_>
      <internalNodes>
        0 -1 153635 4.2046219110488892e-02</internalNodes>
      <leafValues>
        -5.0240474939346313e-01 8.5790568590164185e-01</leafValues></_>
    <_>
      <internalNodes>
        0 -1 20357 -5.8918677270412445e-02</internalNodes>
      <leafValues>
        9.1258633136749268e-01 -3.5142582654953003e-01</leafValues></_>
    <_>
      <internalNodes>
        0 -1 105184 -5.6877447059378028e-04</internalNodes>
      <leafValues>
        -9.7979885339736938e-01 4.2632105946540833e-01</leafValues></_></weakClassifiers></stage4>
</opencv_storage>
